prodata/__init__.py
prodata/preprocessing.py
tests/__init__.py
tests/test_dataproc.py
prodata-0.1.4.dist-info/LICENSE
prodata-0.1.4.dist-info/METADATA
prodata-0.1.4.dist-info/WHEEL
prodata-0.1.4.dist-info/top_level.txt
prodata-0.1.4.dist-info/RECORD
